Songhan1008_pkg/__init__.py
Songhan1008_pkg/mxmulSonghan.py
Songhan1008-0.0.1.dist-info/LICENSE
Songhan1008-0.0.1.dist-info/METADATA
Songhan1008-0.0.1.dist-info/WHEEL
Songhan1008-0.0.1.dist-info/top_level.txt
Songhan1008-0.0.1.dist-info/RECORD
