Metadata-Version: 2.1
Name: Songhan1008
Version: 0.0.1
Summary: An example for PY84 Courses
Home-page: https://github.com/somebody/sampleproject
Author: Songhan
Author-email: songhan@yeah.net
License: UNKNOWN
Platform: UNKNOWN
Classifier: Programming Language :: Python :: 3
Classifier: License :: OSI Approved :: MIT License
Classifier: Operating System :: OS Independent
